{
	"users": [{
		"username": "Eduardo Buzeto",
		"w3id": "carlosbu@br.ibm.com",
		"environments": [{
			"id": "codebakery",
			"projects": [{
				"id": "manageio",
				"type": 1
			}]
		}]
	}, {
		"username": "Rafael Moris",
		"w3id": "rafamos@br.ibm.com",
		"environments": [{
			"id": "codebakery",
			"projects": [{
				"id": "manageio",
				"type": 3
			}]
		}]
	}],
	"types": {
		"1": {
			"id": 1,
			"name": "Administrator"
		},
		"2": {
			"id": 2,
			"name": "Editor"
		},
		"3": {
			"id": 3,
			"name": "Reader"
		}
	}
}
